device_manager_mcp/__init__.py
device_manager_mcp/__main__.py
device_manager_mcp/router.py
device_manager_mcp/server.py
device_manager_mcp/backends/__init__.py
device_manager_mcp/backends/adb.py
device_manager_mcp/backends/scrcpy.py
device_manager_mcp-1.0.7.dist-info/METADATA
device_manager_mcp-1.0.7.dist-info/WHEEL
device_manager_mcp-1.0.7.dist-info/entry_points.txt
device_manager_mcp-1.0.7.dist-info/licenses/LICENSE
device_manager_mcp-1.0.7.dist-info/RECORD
