Metadata-Version: 2.4
Name: device-manager-mcp
Version: 1.0.7
Summary: MCP server for fast Android device interaction with scrcpy acceleration
Project-URL: Homepage, https://github.com/vladkarpman/device-manager-mcp
Project-URL: Repository, https://github.com/vladkarpman/device-manager-mcp
Project-URL: Issues, https://github.com/vladkarpman/device-manager-mcp/issues
Author-email: Vladislav Karpman <vladislavkarpman@gmail.com>
License-Expression: MIT
License-File: LICENSE
Keywords: android,automation,claude,device,mcp,scrcpy,testing
Classifier: Development Status :: 4 - Beta
Classifier: Intended Audience :: Developers
Classifier: License :: OSI Approved :: MIT License
Classifier: Programming Language :: Python :: 3
Classifier: Programming Language :: Python :: 3.11
Classifier: Programming Language :: Python :: 3.12
Classifier: Topic :: Software Development :: Libraries :: Python Modules
Classifier: Topic :: Software Development :: Testing
Requires-Python: >=3.11
Requires-Dist: adbutils>=2.0.0
Requires-Dist: mcp>=1.25.0
Requires-Dist: mysc>=3.0.0
Requires-Dist: numpy>=1.24.0
Requires-Dist: pillow>=10.0.0
Provides-Extra: dev
Requires-Dist: pytest-asyncio>=0.21.0; extra == 'dev'
Requires-Dist: pytest>=7.0.0; extra == 'dev'
